tc_newrelic/__init__.py
tc_newrelic/metrics/__init__.py
tc_newrelic/metrics/newrelic_metrics.py
tc_newrelic-1.0.2.dist-info/licenses/LICENSE
tc_newrelic-1.0.2.dist-info/METADATA
tc_newrelic-1.0.2.dist-info/WHEEL
tc_newrelic-1.0.2.dist-info/top_level.txt
tc_newrelic-1.0.2.dist-info/RECORD
