Metadata-Version: 2.4
Name: tc_newrelic
Version: 1.0.2
Summary: Thumbor metrics extension that forwards metrics to New Relic
Author-email: Your Name <your.email@example.com>
License: MIT License
Project-URL: Homepage, https://github.com/your-username/tc_newrelic
Project-URL: Bug Tracker, https://github.com/your-username/tc_newrelic/issues
Keywords: thumbor,metrics,newrelic
Classifier: Development Status :: 4 - Beta
Classifier: Intended Audience :: Developers
Classifier: License :: OSI Approved :: MIT License
Classifier: Natural Language :: English
Classifier: Operating System :: OS Independent
Classifier: Programming Language :: Python
Classifier: Programming Language :: Python :: 3
Classifier: Programming Language :: Python :: 3.6
Classifier: Programming Language :: Python :: 3.7
Classifier: Programming Language :: Python :: 3.8
Classifier: Programming Language :: Python :: 3.9
Classifier: Programming Language :: Python :: 3.10
Classifier: Programming Language :: Python :: 3.11
Classifier: Topic :: Internet :: WWW/HTTP :: Dynamic Content
Classifier: Topic :: Multimedia :: Graphics :: Presentation
Requires-Python: >=3.6
License-File: LICENSE
Requires-Dist: thumbor>=7.0.0
Requires-Dist: requests>=2.25.0
Provides-Extra: tests
Requires-Dist: pytest; extra == "tests"
Requires-Dist: mock; extra == "tests"
Requires-Dist: flake8; extra == "tests"
Requires-Dist: coverage; extra == "tests"
Dynamic: license-file
